datavizml/__init__.py
datavizml/exploratorydataanalysis.py
datavizml/ppscore.py
datavizml/singledistribution.py
datavizml/utils.py
datavizml-1.16.0.dist-info/licenses/LICENSE
datavizml-1.16.0.dist-info/METADATA
datavizml-1.16.0.dist-info/WHEEL
datavizml-1.16.0.dist-info/top_level.txt
datavizml-1.16.0.dist-info/RECORD
