Metadata-Version: 2.4
Name: datavizml
Version: 1.16.0
Summary: A package to explore and visualise a dataset in preparation for an ML project
Author-email: Dr Robert Dibble <robertdibble@live.co.uk>
Project-URL: Homepage, https://github.com/dibble07/datavizml
Project-URL: Bug Tracker, https://github.com/dibble07/datavizml/issues
Project-URL: Changelog, https://github.com/dibble07/datavizml/releases
Classifier: Programming Language :: Python :: 3.13
Classifier: License :: OSI Approved :: GNU General Public License v3 (GPLv3)
Requires-Python: >=3.11
License-File: LICENSE
Requires-Dist: matplotlib
Requires-Dist: numpy
Requires-Dist: pandas
Requires-Dist: scikit-learn
Requires-Dist: scipy
Requires-Dist: seaborn
Requires-Dist: setuptools<81
Requires-Dist: statsmodels
Requires-Dist: tqdm
Dynamic: license-file
